xargproject/__init__.py
xargproject/attribute.py
xargproject/command.py
xargproject/project.py
xargproject-0.2.dist-info/LICENSE
xargproject-0.2.dist-info/METADATA
xargproject-0.2.dist-info/WHEEL
xargproject-0.2.dist-info/entry_points.txt
xargproject-0.2.dist-info/top_level.txt
xargproject-0.2.dist-info/zip-safe
xargproject-0.2.dist-info/RECORD
