Metadata-Version: 2.1
Name: xargproject
Version: 0.2
Summary: Create a command-line project
Home-page: https://github.com/bondbox/xargproject/
Author: Mingzhe Zou
Author-email: zoumingzhe@outlook.com
License: GPLv2
Project-URL: Source Code, https://github.com/bondbox/xargproject/
Project-URL: Bug Tracker, https://github.com/bondbox/xargproject/issues
Project-URL: Documentation, https://github.com/bondbox/xargproject/
Keywords: command-line,argparse,argcomplete
Platform: any
Classifier: Programming Language :: Python
Classifier: Programming Language :: Python :: 3
Requires-Python: >=3.8
License-File: LICENSE
Requires-Dist: xkits-command >=0.2
